djReact/__init__.py
djReact/frontend/__init__.py
djReact/frontend/frontend.zip
djReact/management/__init__.py
djReact/management/commands/__init__.py
djReact/management/commands/startproject.py
djReact/management/commands/build_dir/__init__.py
djReact/management/commands/build_dir/file_content.py
djReact-2.1.2.data/data/data/frontend.zip
djReact-2.1.2.dist-info/LICENSE
djReact-2.1.2.dist-info/METADATA
djReact-2.1.2.dist-info/WHEEL
djReact-2.1.2.dist-info/entry_points.txt
djReact-2.1.2.dist-info/top_level.txt
djReact-2.1.2.dist-info/RECORD
